<netPeerBinding>
  <binding
    name="string"
    closeTimeout="00:01:00"
    openTimeout="00:01:00"
    receiveTimeout="00:10:00"
    sendTimeout="00:01:00"
    listenIPAddress="String"
    maxBufferPoolSize="524288 "
    maxReceiveMessageSize="65536"
    port="0"
  >
    <security
      mode="None/Transport/Message/TransportWithMessageCredential"
    >
      <message
        clientCredentialType="Certificate/Password"
      />
    </security>
    <readerQuotas
      maxArrayLength="16384"
      maxDepth="32"
      maxStringContentLength="8192"
      maxBytesPerRead="4096"
      maxNameTableCharCount="16384"
    />
    <resolver
      mode="Auto/Custom/Pnrp"
      referralPolicy="DoNotShare/Service/Share"
    >
      <headers>
        <Region xmlns="Uri">"String"</Region>
        <Member xmlns="Uri">"String"</Member>
      </headers>
    </resolver>
  </binding>
</netPeerBinding>
